<?xml version="1.0" encoding="UTF-8" standalone="yes"?>
<object-views xmlns="http://axelor.com/xml/ns/object-views"
  xmlns:xsi="http://www.w3.org/2001/XMLSchema-instance"
  xsi:schemaLocation="http://axelor.com/xml/ns/object-views
  http://axelor.com/xml/ns/object-views/object-views_5.4.xsd">
  
  <selection name="project.task.status.selection" >
    <option value="todo">To-do</option>
    <option value="active">Active</option>
    <option value="complete">Completed</option>
  </selection>
  
  <grid name="project-task-grid" title="Project Tasks" model="com.aop.company.db.ProjectTask">
    <field name="name" title="Task Name"/>
    <field name="task" title="Project Task" />
 	<field name="status" />
 	<field name="priority" />
	<field name="startDate" title="Start Date" />
	<field name="endDate" title="End Date"/>
	<field name="progress" widget="Progress"/>
  </grid>
  
  
  
  <form name="project-task-form" title="Project Task" model="com.aop.company.db.ProjectTask">
    <panel title="Overview">
      <field name="name" title="Task Name"/>
      <field name="task" title="Project Task"  />
      <field name="status"/> 
      <field name="priority" />
      <field name="startDate"/>
      <field name="endDate"/>
      <field name="projs" title="Parent Project" x-type="many-to-one" x-target="com.aop.company.db.Project" x-target-name="name" nameColumn="True" />
      <field name="employee"/>
      <field name="parentTask"/>
      <field name="sequence"/>
      <field name="progress" widget="Progress"/>
  </panel>
  
  <panel-tabs>
  	  <panel title="Notes">
        <field name="notes" showTitle="false" colSpan="12"/>
      </panel>
      
      <panel title="Planning">
        <field name="plannedStartDate"/>
        <field name="plannedDuration"/>
        <field name="plannedProgress"/>
        <spacer/>
        <panel title="Linked project tasks" colSpan="12">
          <field name="finishToStartTaskSet" widget="TagSelect" />
          <field name="startToStartTaskSet" widget="TagSelect" />
          <field name="finishToFinishTaskSet" widget="TagSelect" />
          <field name="startToFinishTaskSet" widget="TagSelect" />
        </panel>
      </panel>
  </panel-tabs>
</form> 


	<gantt name="projectTask-gantt" title="Task Planning" model="com.aop.company.db.ProjectTask"
		  taskStart="plannedStartDate"
		  taskDuration="plannedDuration"
		  taskParent="parentTask"
		  taskSequence="sequence"
		  taskProgress="plannedProgress"
		  x-finish-to-start="finishToStartTaskSet"
		  x-start-to-start="startToStartTaskSet"
		  x-finish-to-finish="finishToFinishTaskSet"
		  x-start-to-finish="startToFinishTaskSet">
		  <field name="name" />
		  <field name="projs" />
		  <field name="employee" />
	</gantt>
	
	
	<calendar name="project.task.calendar" 
			  model="com.aop.company.db.ProjectTask" 
			  colorBy="employee"
			  eventStart="startDate" 
			  eventStop="endDate"  
			  title="ProjectTask Calendar"
			  eventLength="1">
			  <field name="name"/>
	</calendar>
	
	
   
</object-views>